pydeseq2/__init__.py
pydeseq2/__version__.py
pydeseq2/dds.py
pydeseq2/default_inference.py
pydeseq2/ds.py
pydeseq2/grid_search.py
pydeseq2/inference.py
pydeseq2/preprocessing.py
pydeseq2/utils.py
pydeseq2-0.5.2.dist-info/licenses/LICENSE
pydeseq2-0.5.2.dist-info/METADATA
pydeseq2-0.5.2.dist-info/WHEEL
pydeseq2-0.5.2.dist-info/top_level.txt
pydeseq2-0.5.2.dist-info/RECORD
