Metadata-Version: 2.4
Name: pydeseq2
Version: 0.5.2
Summary: A python implementation of DESeq2.
Author: Boris Muzellec, Maria Telenczuk, Vincent Cabelli and Mathieu Andreux
Author-email: boris.muzellec@owkin.com
License: MIT
Requires-Python: >=3.10.0
License-File: LICENSE
Requires-Dist: anndata>=0.11.0
Requires-Dist: formulaic>=1.0.2
Requires-Dist: numpy>=1.23.0
Requires-Dist: pandas>=1.4.0
Requires-Dist: scikit-learn>=1.1.0
Requires-Dist: scipy>=1.11.0
Requires-Dist: formulaic-contrasts>=0.2.0
Requires-Dist: matplotlib>=3.6.2
Provides-Extra: dev
Requires-Dist: pytest>=6.2.4; extra == "dev"
Requires-Dist: pre-commit>=2.13.0; extra == "dev"
Requires-Dist: numpydoc; extra == "dev"
Requires-Dist: coverage; extra == "dev"
Requires-Dist: mypy; extra == "dev"
Requires-Dist: pandas-stubs; extra == "dev"
Dynamic: author
Dynamic: author-email
Dynamic: description
Dynamic: description-content-type
Dynamic: license
Dynamic: license-file
Dynamic: provides-extra
Dynamic: requires-dist
Dynamic: requires-python
Dynamic: summary
